FlopyAdapter/__init__.py
FlopyAdapter/Calculation/InowasFlopyCalculationAdapter.py
FlopyAdapter/Calculation/InowasFlopyImportAdapter.py
FlopyAdapter/Calculation/__init__.py
FlopyAdapter/MfPackages/BasAdapter.py
FlopyAdapter/MfPackages/ChdAdapter.py
FlopyAdapter/MfPackages/DisAdapter.py
FlopyAdapter/MfPackages/DrnAdapter.py
FlopyAdapter/MfPackages/EvtAdapter.py
FlopyAdapter/MfPackages/FhbAdapter.py
FlopyAdapter/MfPackages/GhbAdapter.py
FlopyAdapter/MfPackages/HobAdapter.py
FlopyAdapter/MfPackages/LakAdapter.py
FlopyAdapter/MfPackages/LmtAdapter.py
FlopyAdapter/MfPackages/LpfAdapter.py
FlopyAdapter/MfPackages/MfAdapter.py
FlopyAdapter/MfPackages/NwtAdapter.py
FlopyAdapter/MfPackages/OcAdapter.py
FlopyAdapter/MfPackages/PcgAdapter.py
FlopyAdapter/MfPackages/RchAdapter.py
FlopyAdapter/MfPackages/RivAdapter.py
FlopyAdapter/MfPackages/UpwAdapter.py
FlopyAdapter/MfPackages/WelAdapter.py
FlopyAdapter/MfPackages/__init__.py
FlopyAdapter/MpPackages/BasAdapter.py
FlopyAdapter/MpPackages/MpAdapter.py
FlopyAdapter/MpPackages/SimAdapter.py
FlopyAdapter/MpPackages/__init__.py
FlopyAdapter/MtPackages/AdvAdapter.py
FlopyAdapter/MtPackages/BtnAdapter.py
FlopyAdapter/MtPackages/DspAdapter.py
FlopyAdapter/MtPackages/GcgAdapter.py
FlopyAdapter/MtPackages/LktAdapter.py
FlopyAdapter/MtPackages/MtAdapter.py
FlopyAdapter/MtPackages/PhcAdapter.py
FlopyAdapter/MtPackages/RctAdapter.py
FlopyAdapter/MtPackages/SftAdapter.py
FlopyAdapter/MtPackages/SsmAdapter.py
FlopyAdapter/MtPackages/TobAdapter.py
FlopyAdapter/MtPackages/UztAdapter.py
FlopyAdapter/MtPackages/__init__.py
FlopyAdapter/Read/InowasFlopyReadAdapter.py
FlopyAdapter/Read/InowasFlopyReadFitness.py
FlopyAdapter/Read/InowasModflowReadAdapter.py
FlopyAdapter/Read/ReadBudget.py
FlopyAdapter/Read/ReadConcentration.py
FlopyAdapter/Read/ReadDrawdown.py
FlopyAdapter/Read/ReadFile.py
FlopyAdapter/Read/ReadHead.py
FlopyAdapter/Read/__init__.py
FlopyAdapter/Statistics/HobStatistics.py
FlopyAdapter/Statistics/__init__.py
InowasFlopyAdapter-1.5.0.dist-info/LICENSE.md
InowasFlopyAdapter-1.5.0.dist-info/METADATA
InowasFlopyAdapter-1.5.0.dist-info/WHEEL
InowasFlopyAdapter-1.5.0.dist-info/top_level.txt
InowasFlopyAdapter-1.5.0.dist-info/RECORD
